{"nodes": [{"id": "next_upgrade_skill", "label": "Next.js Upgrade", "file_type": "document", "source_file": "skills/development/next-upgrade/SKILL.md", "source_location": null, "source_url": "https://github.com/vercel-labs/next-skills", "captured_at": null, "author": "vercel-labs", "contributor": null}], "edges": [{"source": "next_upgrade_skill", "target": "next_best_practice_skill", "relation": "semantically_similar_to", "confidence": "INFERRED", "confidence_score": 0.95, "source_file": "skills/development/next-upgrade/SKILL.md", "source_location": null, "weight": 0.95}, {"source": "next_upgrade_skill", "target": "improve_codebase_architecture_skill", "relation": "conceptually_related_to", "confidence": "INFERRED", "confidence_score": 0.65, "source_file": "skills/development/next-upgrade/SKILL.md", "source_location": null, "weight": 0.65}], "hyperedges": []}